MianxiangChengxuyuanDeShujuwajueZhinan/README.md
MianxiangChengxuyuanDeShujuwajueZhinan/__init__.py
MianxiangChengxuyuanDeShujuwajueZhinan/__main__.py
MianxiangChengxuyuanDeShujuwajueZhinan/file.epub
MianxiangChengxuyuanDeShujuwajueZhinan/index.html
MianxiangChengxuyuanDeShujuwajueZhinan/css/__init__.py
MianxiangChengxuyuanDeShujuwajueZhinan/css/annotations.css
MianxiangChengxuyuanDeShujuwajueZhinan/css/main.css
MianxiangChengxuyuanDeShujuwajueZhinan/css/normalize.css
MianxiangChengxuyuanDeShujuwajueZhinan/css/popup.css
MianxiangChengxuyuanDeShujuwajueZhinan/font/__init__.py
MianxiangChengxuyuanDeShujuwajueZhinan/font/fontello.eot
MianxiangChengxuyuanDeShujuwajueZhinan/font/fontello.svg
MianxiangChengxuyuanDeShujuwajueZhinan/font/fontello.ttf
MianxiangChengxuyuanDeShujuwajueZhinan/font/fontello.woff
MianxiangChengxuyuanDeShujuwajueZhinan/img/__init__.py
MianxiangChengxuyuanDeShujuwajueZhinan/img/annotator-glyph-sprite.png
MianxiangChengxuyuanDeShujuwajueZhinan/img/annotator-icon-sprite.png
MianxiangChengxuyuanDeShujuwajueZhinan/img/apple-touch-icon.png
MianxiangChengxuyuanDeShujuwajueZhinan/img/cancelfullscreen.png
MianxiangChengxuyuanDeShujuwajueZhinan/img/close.png
MianxiangChengxuyuanDeShujuwajueZhinan/img/fullscreen.png
MianxiangChengxuyuanDeShujuwajueZhinan/img/loader.gif
MianxiangChengxuyuanDeShujuwajueZhinan/img/menu-icon.png
MianxiangChengxuyuanDeShujuwajueZhinan/img/save.png
MianxiangChengxuyuanDeShujuwajueZhinan/img/saved.png
MianxiangChengxuyuanDeShujuwajueZhinan/img/settings-s.png
MianxiangChengxuyuanDeShujuwajueZhinan/img/settings.png
MianxiangChengxuyuanDeShujuwajueZhinan/img/star.png
MianxiangChengxuyuanDeShujuwajueZhinan/js/__init__.py
MianxiangChengxuyuanDeShujuwajueZhinan/js/epub.js
MianxiangChengxuyuanDeShujuwajueZhinan/js/epub.min.js
MianxiangChengxuyuanDeShujuwajueZhinan/js/epub.min.map
MianxiangChengxuyuanDeShujuwajueZhinan/js/hooks.min.js
MianxiangChengxuyuanDeShujuwajueZhinan/js/hooks.min.map
mianxiang_chengxuyuan_de_shujuwajue_zhinan-2024.2.29.0.dist-info/METADATA
mianxiang_chengxuyuan_de_shujuwajue_zhinan-2024.2.29.0.dist-info/WHEEL
mianxiang_chengxuyuan_de_shujuwajue_zhinan-2024.2.29.0.dist-info/entry_points.txt
mianxiang_chengxuyuan_de_shujuwajue_zhinan-2024.2.29.0.dist-info/top_level.txt
mianxiang_chengxuyuan_de_shujuwajue_zhinan-2024.2.29.0.dist-info/RECORD
